MANIFEST.in
README.txt
setup.py
docs/COPYRIGHT.txt
docs/HISTORY.txt
docs/LICENSE.txt
src/cromlech/__init__.py
src/cromlech.container.egg-info/PKG-INFO
src/cromlech.container.egg-info/SOURCES.txt
src/cromlech.container.egg-info/dependency_links.txt
src/cromlech.container.egg-info/entry_points.txt
src/cromlech.container.egg-info/namespace_packages.txt
src/cromlech.container.egg-info/not-zip-safe
src/cromlech.container.egg-info/requires.txt
src/cromlech.container.egg-info/top_level.txt
src/cromlech/container/README.txt
src/cromlech/container/__init__.py
src/cromlech/container/components.py
src/cromlech/container/constraints.py
src/cromlech/container/contained.py
src/cromlech/container/interfaces.py
src/cromlech/container/size.py
src/cromlech/container/tests/__init__.py
src/cromlech/container/tests/test_constraints.py
src/cromlech/container/tests/test_contained.py
src/cromlech/container/tests/test_contained_event.py
src/cromlech/container/tests/test_container.py
src/cromlech/container/tests/test_dispatch.txt
src/cromlech/container/tests/test_namechooser.py
src/cromlech/container/tests/test_setitem.py
src/cromlech/container/tests/test_size.py
src/cromlech/container/tests/test_sublocations.py
src/cromlech/container/tests/test_uncontained.py