Metadata-Version: 1.0
Name: cromlech.container
Version: 0.1
Summary: Cromlech Web Framework container components definitions.
Home-page: http://gitweb.dolmen-project.org/
Author: The Dolmen team
Author-email: dolmen@list.dolmen-project.org
License: ZPL
Keywords: Cromlech Dolmen Framework
Platform: UNKNOWN
Classifier: Programming Language :: Python
